[
  {
    "id": 1,
    "userId": 1,
    "type": "crypto",
    "number": "4000656684230545",
    "expiry": "03/28",
    "cvv": "709",
    "balance": "0.00",
    "btcBalance": "0.00000000",
    "ethBalance": "0.00000000",
    "btcAddress": "1ZCjvw4Qxx4JhDGXJw577riMZCrw4",
    "ethAddress": "0x5B9EC904fd39A1aD277D2BABD08ce1cb4E49d752"
  },
  {
    "id": 2,
    "userId": 1,
    "type": "usd",
    "number": "4111891201988062",
    "expiry": "03/28",
    "cvv": "495",
    "balance": "0.00",
    "btcBalance": "0.00000000",
    "ethBalance": "0.00000000",
    "btcAddress": null,
    "ethAddress": null
  },
  {
    "id": 3,
    "userId": 1,
    "type": "uah",
    "number": "5555624368885501",
    "expiry": "03/28",
    "cvv": "989",
    "balance": "0.00",
    "btcBalance": "0.00000000",
    "ethBalance": "0.00000000",
    "btcAddress": null,
    "ethAddress": null
  },
  {
    "id": 4,
    "userId": 2,
    "type": "crypto",
    "number": "4000589306345761",
    "expiry": "06/28",
    "cvv": "863",
    "balance": "0",
    "btcBalance": "0.001",
    "ethBalance": "0.01",
    "btcAddress": "1zXkpRLC67Ddo99J2j6VcfDBb2xRE",
    "ethAddress": "0xd23cb21D7a7076EDc2631bc886021E4171117D9c"
  },
  {
    "id": 5,
    "userId": 2,
    "type": "usd",
    "number": "4111238058472974",
    "expiry": "09/28",
    "cvv": "919",
    "balance": "1000",
    "btcBalance": "0",
    "ethBalance": "0",
    "btcAddress": null,
    "ethAddress": null
  },
  {
    "id": 6,
    "userId": 2,
    "type": "uah",
    "number": "5555248950789491",
    "expiry": "08/28",
    "cvv": "823",
    "balance": "40000",
    "btcBalance": "0",
    "ethBalance": "0",
    "btcAddress": null,
    "ethAddress": null
  },
  {
    "id": 13,
    "userId": 5,
    "type": "crypto",
    "number": "4000101461947771",
    "expiry": "10/28",
    "cvv": "240",
    "balance": "0",
    "btcBalance": "968396.02",
    "ethBalance": "179864.09",
    "btcAddress": "1h7T0xUSFZpwg7uY8Jhho8hwhRWzD",
    "ethAddress": "0x0f2178a1c174697D0a43B654C583c7074bdbcA8C"
  },
  {
    "id": 14,
    "userId": 5,
    "type": "usd",
    "number": "4111323103306819",
    "expiry": "01/28",
    "cvv": "761",
    "balance": "200000000",
    "btcBalance": "0",
    "ethBalance": "0",
    "btcAddress": null,
    "ethAddress": null
  },
  {
    "id": 15,
    "userId": 5,
    "type": "uah",
    "number": "5555423163670631",
    "expiry": "12/28",
    "cvv": "349",
    "balance": "400000000",
    "btcBalance": "0",
    "ethBalance": "0",
    "btcAddress": null,
    "ethAddress": null
  },
  {
    "id": 16,
    "userId": 6,
    "type": "crypto",
    "number": "4111330535985631",
    "expiry": "03/28",
    "cvv": "696",
    "balance": "0.00",
    "btcBalance": "0.00000000",
    "ethBalance": "0.00000000",
    "btcAddress": "1J5SPn5BuapY9trKq47hduwg5ZQpB",
    "ethAddress": "0x433f44402843B3ef3eB52EEe47F75D1F473568D7"
  },
  {
    "id": 17,
    "userId": 6,
    "type": "usd",
    "number": "4112185546212195",
    "expiry": "03/28",
    "cvv": "614",
    "balance": "0.00",
    "btcBalance": "0.00000000",
    "ethBalance": "0.00000000",
    "btcAddress": null,
    "ethAddress": null
  },
  {
    "id": 18,
    "userId": 6,
    "type": "uah",
    "number": "4113271946207582",
    "expiry": "03/28",
    "cvv": "338",
    "balance": "0.00",
    "btcBalance": "0.00000000",
    "ethBalance": "0.00000000",
    "btcAddress": null,
    "ethAddress": null
  },
  {
    "id": 19,
    "userId": 7,
    "type": "crypto",
    "number": "4111413957644346",
    "expiry": "03/28",
    "cvv": "960",
    "balance": "0.00",
    "btcBalance": "0.00000000",
    "ethBalance": "0.00000000",
    "btcAddress": "17KUPqLMFgggvgT6DNTwYxaZ1N5GU",
    "ethAddress": "0xbB9a7A2318A045E45c5ACbea61ADC1acd8C6721E"
  },
  {
    "id": 20,
    "userId": 7,
    "type": "usd",
    "number": "4112818239176215",
    "expiry": "03/28",
    "cvv": "373",
    "balance": "0.00",
    "btcBalance": "0.00000000",
    "ethBalance": "0.00000000",
    "btcAddress": null,
    "ethAddress": null
  },
  {
    "id": 21,
    "userId": 7,
    "type": "uah",
    "number": "4113633308331620",
    "expiry": "03/28",
    "cvv": "630",
    "balance": "0.00",
    "btcBalance": "0.00000000",
    "ethBalance": "0.00000000",
    "btcAddress": null,
    "ethAddress": null
  },
  {
    "id": 22,
    "userId": 8,
    "type": "crypto",
    "number": "4111660863622836",
    "expiry": "03/28",
    "cvv": "940",
    "balance": "0.00",
    "btcBalance": "0.00000000",
    "ethBalance": "0.00000000",
    "btcAddress": "1U7mR7rmXgA1o8gYuh3bDxR9Nat99",
    "ethAddress": "0xDDE51dC0920321b0c29a6B950d9D98FFeC35413f"
  },
  {
    "id": 23,
    "userId": 8,
    "type": "usd",
    "number": "4112473829066479",
    "expiry": "03/28",
    "cvv": "735",
    "balance": "0.00",
    "btcBalance": "0.00000000",
    "ethBalance": "0.00000000",
    "btcAddress": null,
    "ethAddress": null
  },
  {
    "id": 24,
    "userId": 8,
    "type": "uah",
    "number": "4113851669913815",
    "expiry": "03/28",
    "cvv": "766",
    "balance": "0.00",
    "btcBalance": "0.00000000",
    "ethBalance": "0.00000000",
    "btcAddress": null,
    "ethAddress": null
  }
]